{
	"credit": "Made with Blockbench",
	"textures": {
		"0": "industrialupgrade:block/wiring/heatcool/heatcool_pipes",
		"particle": "industrialupgrade:block/wiring/heatcool/heatcool_pipes"
	},
	"elements": [
		{
			"from": [6, 6, 6],
			"to": [10, 10, 10],
			"faces": {
				"north": {"uv": [6, 6, 10, 10], "texture": "#0"},
				"east": {"uv": [6, 6, 10, 10], "texture": "#0"},
				"south": {"uv": [6, 6, 10, 10], "texture": "#0"},
				"west": {"uv": [6, 6, 10, 10], "texture": "#0"},
				"up": {"uv": [6, 6, 10, 10], "texture": "#0"},
				"down": {"uv": [6, 6, 10, 10], "texture": "#0"}
			}
		}
	],
	"display": {
		"thirdperson_righthand": {
			"rotation": [75, 45, 0],
			"translation": [0, 2.5, 0]
		},
		"thirdperson_lefthand": {
			"rotation": [75, 45, 0],
			"translation": [0, 2.5, 0]
		},
		"firstperson_righthand": {
			"rotation": [0, 45, 0]
		},
		"firstperson_lefthand": {
			"rotation": [0, 225, 0]
		},
		"ground": {
			"translation": [0, 3, 0]
		},
		"gui": {
			"rotation": [30, 225, 0],
			"scale": [1.4, 1.4, 1.4]
		}
	}
}