{
  "variants": {
    "facing=north,type=per_comb_pump": {
      "model": "industrialupgrade:block/basemachine/per_comb_pump"
    },
    "facing=south,type=per_comb_pump": {
      "model": "industrialupgrade:block/basemachine/per_comb_pump",
      "y": 180
    },
    "facing=west,type=per_comb_pump": {
      "model": "industrialupgrade:block/basemachine/per_comb_pump",
      "y": 270
    },
    "facing=east,type=per_comb_pump": {
      "model": "industrialupgrade:block/basemachine/per_comb_pump",
      "y": 90
    },
    "facing=down,type=per_comb_pump": {
      "model": "industrialupgrade:block/basemachine/per_comb_pump",
      "x": 90
    },
    "facing=up,type=per_comb_pump": {
      "model": "industrialupgrade:block/basemachine/per_comb_pump",
      "x": 270
    },
    "facing=north,type=per_comb_pump_invalid": {
      "model": "industrialupgrade:block/basemachine/per_comb_pump_active"
    },
    "facing=south,type=per_comb_pump_invalid": {
      "model": "industrialupgrade:block/basemachine/per_comb_pump_active",
      "y": 180
    },
    "facing=west,type=per_comb_pump_invalid": {
      "model": "industrialupgrade:block/basemachine/per_comb_pump_active",
      "y": 270
    },
    "facing=east,type=per_comb_pump_invalid": {
      "model": "industrialupgrade:block/basemachine/per_comb_pump_active",
      "y": 90
    },
    "facing=down,type=per_comb_pump_invalid": {
      "model": "industrialupgrade:block/basemachine/per_comb_pump_active",
      "x": 90
    },
    "facing=up,type=per_comb_pump_invalid": {
      "model": "industrialupgrade:block/basemachine/per_comb_pump_active",
      "x": 270
    },
    "facing=north,type=per_comb_pump_active": {
      "model": "industrialupgrade:block/basemachine/per_comb_pump_active"
    },
    "facing=south,type=per_comb_pump_active": {
      "model": "industrialupgrade:block/basemachine/per_comb_pump_active",
      "y": 180
    },
    "facing=west,type=per_comb_pump_active": {
      "model": "industrialupgrade:block/basemachine/per_comb_pump_active",
      "y": 270
    },
    "facing=east,type=per_comb_pump_active": {
      "model": "industrialupgrade:block/basemachine/per_comb_pump_active",
      "y": 90
    },
    "facing=down,type=per_comb_pump_active": {
      "model": "industrialupgrade:block/basemachine/per_comb_pump_active",
      "x": 90
    },
    "facing=up,type=per_comb_pump_active": {
      "model": "industrialupgrade:block/basemachine/per_comb_pump_active",
      "x": 270
    }
  }
}