{
  "type": "minecraft:crafting_shaped",
  "key": {
    "A": {
      "item": "industrialupgrade:basemachine2/analyzer"
    },
    "B": {
      "type": "forge:nbt",
      "count": 1,
      "item": "industrialupgrade:circuit/quantumcircuit",
      "nbt": "{level:7}"
    },
    "C": {
      "item": "industrialupgrade:module_schedule"
    },
    "D": {
      "tag": "forge:ingots/germanium"
    }
  },
  "pattern": [
    "BAB",
    "DCD",
    "   "
  ],
  "result": {
    "item": "industrialupgrade:analyzermodule"
  }
}