{
  "type": "minecraft:crafting_shaped",
  "key": {
    "A": {
      "item": "industrialupgrade:basemachine3/adv_replicator"
    },
    "B": {
      "item": "industrialupgrade:crafting_elements/crafting_93_element"
    },
    "C": {
      "item": "industrialupgrade:crafting_elements/crafting_96_element"
    },
    "D": {
      "item": "industrialupgrade:crafting_elements/crafting_139_element"
    },
    "E": {
      "item": "industrialupgrade:crafting_elements/crafting_83_element"
    }
  },
  "pattern": [
    "DED",
    "CAB",
    "D D"
  ],
  "result": {
    "item": "industrialupgrade:basemachine3/imp_replicator"
  }
}