{
  "type": "minecraft:crafting_shaped",
  "category": "misc",
  "key": {
    "A": [
      {
        "item": "industrialupgrade:crafting_elements/crafting_376_element"
      }
    ],
    "B": [
      {
        "tag": "forge:plates/magnesium"
      }
    ],
    "C": [
      {
        "item": "industrialupgrade:crafting_elements/crafting_453_element"
      }
    ]
  },
  "pattern": [
    "AA ",
    "BC ",
    "   "
  ],
  "result": {
    "count": 2,
    "item": "industrialupgrade:crafting_elements/crafting_393_element"
  },
  "show_notification": true
}