{
  "type": "industrialupgrade:shaped_recipe",
  "key": {
    "A": {
      "item": "industrialupgrade:blockresource/advanced_machine"
    },
    "B": {
      "item": "industrialupgrade:crafting_elements/crafting_60_element"
    },
    "C": {
      "item": "industrialupgrade:crafting_elements/crafting_51_element"
    },
    "D": {
      "item": "industrialupgrade:crafting_elements/crafting_243_element"
    },
    "E": {
      "item": "industrialupgrade:crafting_elements/crafting_130_element"
    },
    "F": {
      "item": "industrialupgrade:crafting_elements/crafting_44_element"
    }
  },
  "pattern": [
    "DFE",
    "CAC",
    " B "
  ],
  "result": {
    "item": "industrialupgrade:basemachine3/autocrafter"
  }
}