{
  "type": "minecraft:crafting_shaped",
  "key": {
    "A": [
      {
        "tag": "forge:doubleplate/alumel"
      }
    ],
    "B": [
      {
        "tag": "forge:doubleplate/aluminium"
      }
    ],
    "D": {
      "type": "forge:nbt",
      "count": 1,
      "item": "industrialupgrade:circuit/nanocircuit",
      "nbt": "{level:5}"
    },
    "E": [
      {
        "item": "industrialupgrade:nanobox"
      }
    ]
  },
  "pattern": [
    "ABA",
    "D D",
    "EEE"
  ],
  "result": {
    "item": "industrialupgrade:upgradekitmachine/upgradepanelkitmachine"
  }
}