{
  "type": "minecraft:crafting_shaped",
  "key": {
    "A": [
      {
        "item": "industrialupgrade:crafting_elements/crafting_21_element"
      }
    ],
    "B": [
      {
        "item": "industrialupgrade:itemdust/nanoactivated_mixture_dust"
      }
    ],
    "C": [
      {
        "item": "industrialupgrade:itemdust/emerald_dust"
      }
    ],
    "D": [
      {
        "tag": "forge:plates/ferromanganese"
      }
    ],
    "E": [
      {
        "tag": "forge:plates/aluminumbronze"
      }
    ]
  },
  "pattern": [
    "EBE",
    "CAC",
    "DBD"
  ],
  "result": {
    "item": "industrialupgrade:crafting_elements/crafting_671_element"
  }
}