{
  "type": "industrialupgrade:shaped_recipe",
  "category": "misc",
  "key": {
    "A": {
      "item": "industrialupgrade:hydro_turbine/hydro_turbine_casing_1"
    },
    "B": {
      "item": "industrialupgrade:electronic_stabilizers"
    },
    "C": {
      "item": "industrialupgrade:crafting_elements/crafting_599_element"
    },
    "D": {
      "item": "industrialupgrade:photoniy_ingot"
    },
    "E": {
      "item": "industrialupgrade:crafting_elements/crafting_594_element"
    }
  },
  "pattern": [
    "DCD",
    "BAB",
    " E "
  ],
  "result": {
    "count": 1,
    "id": "industrialupgrade:hydro_turbine/hydro_turbine_stabilizer"
  },
  "show_notification": false
}