{
  "type": "industrialupgrade:shaped_recipe",
  "category": "misc",
  "key": {
    "A": {
      "item": "industrialupgrade:quarrymodules/kar2"
    },
    "B": {
      "item": "industrialupgrade:photoniy_ingot"
    },
    "C": {
      "type": "neoforge:components",
      "components": {
        "industrialupgrade:level_microchip": 10,
        "minecraft:attribute_modifiers": {
          "modifiers": []
        },
        "minecraft:enchantments": {
          "levels": {}
        },
        "minecraft:lore": [],
        "minecraft:max_stack_size": 64,
        "minecraft:rarity": "common",
        "minecraft:repair_cost": 0
      },
      "items": "industrialupgrade:circuit/spectralcircuit"
    }
  },
  "pattern": [
    "ABA",
    "BCB",
    "ABA"
  ],
  "result": {
    "count": 1,
    "id": "industrialupgrade:quarrymodules/kar3"
  },
  "show_notification": false
}