{
  "display" : {
    "icon" : {
      "item" : "industrialupgrade:machines",
      "data" : 11
    },
    "title" : {
      "translate" : "achievement.had_panel"
    },
    "description" : {
      "translate" : "achievement.had_panel.desc"
    },
    "frame" : "challenge"
  },
  "parent" : "industrialupgrade:main/had_core",
  "criteria" : {
    "mine" : {
      "trigger" : "minecraft:inventory_changed",
      "conditions" : {
        "items" : [
          {
            "item" : "industrialupgrade:machines",
            "data" : 11
          }
        ]
      }
    }
  }
}
