{
  "parent" : "block/cube",
  "textures" : {
    "particle" : "industrialupgrade:block/blockcombmacerator1_side",
    "down" : "industrialupgrade:block/blockcombmacerator1_side",
    "up" : "industrialupgrade:block/blockcombmacerator1_top",
    "north" : "industrialupgrade:block/blockcombmacerator1_main",
    "east" : "industrialupgrade:block/blockcombmacerator1_side",
    "south" : "industrialupgrade:block/blockcombmacerator1_side",
    "west" : "industrialupgrade:block/blockcombmacerator1_side"
  }
}
