{
  "parent" : "block/cube",
  "textures" : {
    "particle" : "industrialupgrade:blocks/blockfermer3_bottom",
    "down" : "industrialupgrade:blocks/blockfermer3_bottom",
    "up" : "industrialupgrade:blocks/blockfermer3_top_active",
    "north" : "industrialupgrade:blocks/blockfermer3_main_active",
    "east" : "industrialupgrade:blocks/blockfermer3_side_active",
    "south" : "industrialupgrade:blocks/blockfermer3_side2_active",
    "west" : "industrialupgrade:blocks/blockfermer3_side_active"
  }
}
