{
  "variants": {
    "facing=north,type=geothermal_casing": {
      "model": "industrialupgrade:block/geothermalpump/geothermal_casing"
    },
    "facing=south,type=geothermal_casing": {
      "model": "industrialupgrade:block/geothermalpump/geothermal_casing",
      "y": 180
    },
    "facing=west,type=geothermal_casing": {
      "model": "industrialupgrade:block/geothermalpump/geothermal_casing",
      "y": 270
    },
    "facing=east,type=geothermal_casing": {
      "model": "industrialupgrade:block/geothermalpump/geothermal_casing",
      "y": 90
    },
    "facing=down,type=geothermal_casing": {
      "model": "industrialupgrade:block/geothermalpump/geothermal_casing",
      "x": 90
    },
    "facing=up,type=geothermal_casing": {
      "model": "industrialupgrade:block/geothermalpump/geothermal_casing",
      "x": 270
    },
    "facing=north,type=geothermal_casing_invalid": {
      "model": "industrialupgrade:block/geothermalpump/geothermal_casing"
    },
    "facing=south,type=geothermal_casing_invalid": {
      "model": "industrialupgrade:block/geothermalpump/geothermal_casing",
      "y": 180
    },
    "facing=west,type=geothermal_casing_invalid": {
      "model": "industrialupgrade:block/geothermalpump/geothermal_casing",
      "y": 270
    },
    "facing=east,type=geothermal_casing_invalid": {
      "model": "industrialupgrade:block/geothermalpump/geothermal_casing",
      "y": 90
    },
    "facing=down,type=geothermal_casing_invalid": {
      "model": "industrialupgrade:block/geothermalpump/geothermal_casing",
      "x": 90
    },
    "facing=up,type=geothermal_casing_invalid": {
      "model": "industrialupgrade:block/geothermalpump/geothermal_casing",
      "x": 270
    }
  }
}